moviemanagement/__init__.py
moviemanagement/movie_client.py
moviemanagement/movie_config.py
moviemanagement/schemas/__init__.py
moviemanagement/schemas/schemas.py
moviemanagement-0.0.4.dist-info/METADATA
moviemanagement-0.0.4.dist-info/WHEEL
moviemanagement-0.0.4.dist-info/top_level.txt
moviemanagement-0.0.4.dist-info/RECORD
