Metadata-Version: 2.4
Name: moviemanagement
Version: 0.0.4
Summary: Package for Movie Management API
Author: Rene, Cybelle, Giovani
Requires-Python: >=3.10
Requires-Dist: httpx>=0.28.1
Requires-Dist: pydantic>=2.0.0
Requires-Dist: backoff>=2.2.1
Requires-Dist: python-dotenv
